license_control/1.py
license_control/__init__.py
license_control/core.py
license_control/license_control.py
tests/__init__.py
tests/test_core.py
license_control-0.0.3.dist-info/LICENSE
license_control-0.0.3.dist-info/METADATA
license_control-0.0.3.dist-info/WHEEL
license_control-0.0.3.dist-info/top_level.txt
license_control-0.0.3.dist-info/RECORD
