Metadata-Version: 2.1
Name: license_control
Version: 0.0.3
Summary: A comprehensive license management module
Home-page: https://github.com/Shunlly/license_control
Author: chenshuhang
Author-email: a330289953@gmail.com
Keywords: license control,licensing
Classifier: Development Status :: 3 - Alpha
Classifier: Intended Audience :: Developers
Classifier: License :: OSI Approved :: MIT License
Classifier: Programming Language :: Python :: 3.12
Requires-Python: >=3.7
License-File: LICENSE
Requires-Dist: cryptography>=3.4.7
